aioredis_semaphore/__init__.py
aioredis_semaphore-0.1.0.dist-info/WHEEL
aioredis_semaphore-0.1.0.dist-info/LICENSE
aioredis_semaphore-0.1.0.dist-info/METADATA
aioredis_semaphore-0.1.0.dist-info/RECORD
