Metadata-Version: 2.1
Name: aioredis-semaphore
Version: 0.1.0
Summary: 
Author: David Jiménez
Author-email: davigetto@gmail.com
Requires-Python: >=3.8,<4.0
Classifier: Programming Language :: Python :: 3
Classifier: Programming Language :: Python :: 3.8
Classifier: Programming Language :: Python :: 3.9
Classifier: Programming Language :: Python :: 3.10
Classifier: Programming Language :: Python :: 3.11
Requires-Dist: aioredis (>=2.0.1,<3.0.0)
